enum4linux/__init__.py
enum4linux/__main__.py
enum4linux/dependencies.py
enum4linux.py-0.0.0a1.dist-info/LICENSE
enum4linux.py-0.0.0a1.dist-info/METADATA
enum4linux.py-0.0.0a1.dist-info/WHEEL
enum4linux.py-0.0.0a1.dist-info/entry_points.txt
enum4linux.py-0.0.0a1.dist-info/top_level.txt
enum4linux.py-0.0.0a1.dist-info/RECORD
