Metadata-Version: 2.1
Name: enum4linux.py
Version: 0.0.0a1
Summary: Port for enum4linux perl script
Home-page: https://github.com/onlinejudge95/enum4linux.py
Author: onlinejudge95
Author-email: onlinejudge95@gmail.com
License: GNU GPLv2
Platform: UNKNOWN
Requires-Dist: setuptools (==51.0.0)
Requires-Dist: click (==7.1.2)
